odoo/addons/l10n_ch_bank/README.rst
odoo/addons/l10n_ch_bank/__init__.py
odoo/addons/l10n_ch_bank/__manifest__.py
odoo/addons/l10n_ch_bank/hooks.py
odoo/addons/l10n_ch_bank/data/res.bank.csv
odoo/addons/l10n_ch_bank/i18n/de.po
odoo/addons/l10n_ch_bank/i18n/fr.po
odoo/addons/l10n_ch_bank/i18n/it.po
odoo/addons/l10n_ch_bank/i18n/l10n_ch_bank.pot
odoo/addons/l10n_ch_bank/models/__init__.py
odoo/addons/l10n_ch_bank/models/bank.py
odoo/addons/l10n_ch_bank/readme/CONTRIBUTORS.rst
odoo/addons/l10n_ch_bank/readme/DESCRIPTION.rst
odoo/addons/l10n_ch_bank/readme/USAGE.rst
odoo/addons/l10n_ch_bank/static/description/icon.png
odoo/addons/l10n_ch_bank/static/description/index.html
odoo12_addon_l10n_ch_bank-12.0.1.0.0.99.dev5.dist-info/METADATA
odoo12_addon_l10n_ch_bank-12.0.1.0.0.99.dev5.dist-info/WHEEL
odoo12_addon_l10n_ch_bank-12.0.1.0.0.99.dev5.dist-info/top_level.txt
odoo12_addon_l10n_ch_bank-12.0.1.0.0.99.dev5.dist-info/RECORD
